LICENSE.txt
MANIFEST.in
README.rst
requirements.txt
setup.cfg
setup.py
doc/Makefile
doc/make.bat
doc/source/conf.py
doc/source/development.rst
doc/source/examples.rst
doc/source/gym.rst
doc/source/index.rst
doc/source/installation.rst
doc/source/quickstart.rst
doc/source/reprise.png
doc/source/reprise.rst
doc/source/theory.rst
doc/source/_static/copybutton.js
reprise/__init__.py
reprise/action_inference.py
reprise/context_inference.py
reprise.egg-info/PKG-INFO
reprise.egg-info/SOURCES.txt
reprise.egg-info/dependency_links.txt
reprise.egg-info/requires.txt
reprise.egg-info/top_level.txt
reprise/gym/__init__.py
reprise/gym/rocketball/__init__.py
reprise/gym/rocketball/agent.py
reprise/gym/rocketball/config.py
reprise/gym/rocketball/gui.py
reprise/gym/rocketball/gui_attributes.py
reprise/gym/rocketball/obstacle.py
reprise/gym/rocketball/rocketball_env.py
reprise/gym/rocketball/terrain.py
tests/__init__.py
tests/model.py
tests/test_action_inference.py
tests/test_context_inference.py
tests/test_reprise.py
tests/references/test_reprise_actions.npy
tests/references/test_reprise_contexts.npy