Metadata-Version: 2.1
Name: reprise
Version: 1.0.0
Summary: REtrospective and PRospective Inference SchEme
Home-page: https://github.com/CognitiveModeling/reprise
Author: Fedor Scholz
Author-email: fedor.scholz@posteo.net
License: MIT
Platform: Linux
Classifier: Development Status :: 3 - Alpha
Classifier: Environment :: Console
Classifier: Intended Audience :: Science/Research
Classifier: License :: OSI Approved :: MIT License
Classifier: Operating System :: POSIX :: Linux
Classifier: Programming Language :: Python
Classifier: Programming Language :: Python :: 3.7
Classifier: Programming Language :: Python :: 3.8
Classifier: Programming Language :: Python :: 3 :: Only
Classifier: Topic :: Scientific/Engineering
Classifier: Topic :: Scientific/Engineering :: Artificial Intelligence
Provides-Extra: tests
Provides-Extra: docs
